README.md
setup.py
jibu.egg-info/PKG-INFO
jibu.egg-info/SOURCES.txt
jibu.egg-info/dependency_links.txt
jibu.egg-info/top_level.txt
package/__init__.py
package/__jibUrl.py
package/_locust.py