Metadata-Version: 1.0
Name: jibu
Version: 1.0
Summary: this is a test
Home-page: UNKNOWN
Author: UNKNOWN
Author-email: UNKNOWN
License: MIT
Platform: UNKNOWN
